cmd_chat/__init__.py
cmd_chat/client/client.py
cmd_chat/client/config.py
cmd_chat/client/core/crypto.py
cmd_chat/client/core/abs/abs_crypto.py
cmd_chat/server/models.py
cmd_chat/server/server.py
cmd_chat/server/services.py
secured_console_chat-1.1.21.dist-info/LICENSE
secured_console_chat-1.1.21.dist-info/METADATA
secured_console_chat-1.1.21.dist-info/WHEEL
secured_console_chat-1.1.21.dist-info/entry_points.txt
secured_console_chat-1.1.21.dist-info/top_level.txt
secured_console_chat-1.1.21.dist-info/RECORD
