Metadata-Version: 2.1
Name: secured-console-chat
Version: 1.1.21
Summary: Secured console chat with RSA & Fernet
Home-page: https://github.com/dinosaurtirex/cmd-chat
Author: dinosaurtirex
Author-email: sneakybeaky18@gmail.com
License: MIT
Requires-Python: >=3.10
License-File: LICENSE
Requires-Dist: sanic
Requires-Dist: requests
Requires-Dist: rsa
Requires-Dist: cryptography
Requires-Dist: colorama
Requires-Dist: pydantic
Requires-Dist: websocket-client
